MANIFEST.in
README.md
requirements.txt
setup.cfg
setup.py
zamba/__init__.py
zamba/cli.py
zamba.egg-info/PKG-INFO
zamba.egg-info/SOURCES.txt
zamba.egg-info/dependency_links.txt
zamba.egg-info/entry_points.txt
zamba.egg-info/requires.txt
zamba.egg-info/top_level.txt
zamba/models/__init__.py
zamba/models/cnnensemble_model.py
zamba/models/manager.py
zamba/models/metrics.py
zamba/models/model.py
zamba/models/cnnensemble/Readme.txt
zamba/models/cnnensemble/__init__.py
zamba/models/cnnensemble/requirements.txt
zamba/models/cnnensemble/src/__init__.py
zamba/models/cnnensemble/src/add_paths.py
zamba/models/cnnensemble/src/config.py
zamba/models/cnnensemble/src/generate_folds.py
zamba/models/cnnensemble/src/metrics.py
zamba/models/cnnensemble/src/second_stage.py
zamba/models/cnnensemble/src/select_usused_clips.py
zamba/models/cnnensemble/src/single_frame_cnn.py
zamba/models/cnnensemble/src/utils.py