Metadata-Version: 2.1
Name: zamba
Version: 0.1.5
Summary: Zamba is a tool to identify the species seen in camera trap videos from sites in central Africa.
Home-page: http://zamba.drivendata.org
Author: DrivenData
Author-email: info@drivendata.org
License: UNKNOWN
Download-URL: https://github.com/drivendataorg/zamba/archive/0.1.tar.gz
Project-URL: Homepage, http://zamba.drivendata.org
Project-URL: Documentation, http://zamba.drivendata.org/docs/
Project-URL: Source Code, https://github.com/drivendataorg/zamba
Project-URL: DrivenData, http://drivendata.co
Keywords: deep learning,camera,africa,classifier
Platform: UNKNOWN
Classifier: Development Status :: 3 - Alpha
Classifier: Intended Audience :: Developers
Classifier: Intended Audience :: Science/Research
Classifier: License :: OSI Approved :: MIT License
Classifier: Programming Language :: Python :: 3
Classifier: Programming Language :: Python :: 3.5
Classifier: Programming Language :: Python :: 3.6
Classifier: Topic :: Scientific/Engineering
Classifier: Topic :: Scientific/Engineering :: Artificial Intelligence
Classifier: Topic :: Scientific/Engineering :: Image Recognition
Classifier: Topic :: Multimedia :: Video
Requires-Python: >=3.5
Provides-Extra: gpu
Provides-Extra: cpu
